des/__init__.py
des/admin.py
des/apps.py
des/backends.py
des/forms.py
des/helpers.py
des/models.py
des/urls.py
des/views.py
des/migrations/0001_initial.py
des/migrations/__init__.py
des/static/css/des.css
des/static/js/des.js
des/templates/des/change_form.html
des/templates/des/test_email.html
des/templates/des/test_email.txt
django_des-2.4.1.dist-info/DESCRIPTION.rst
django_des-2.4.1.dist-info/METADATA
django_des-2.4.1.dist-info/RECORD
django_des-2.4.1.dist-info/WHEEL
django_des-2.4.1.dist-info/metadata.json
django_des-2.4.1.dist-info/top_level.txt
